reserve_name/__init__.py
reserve_name/cli.py
reserve_name-0.1.2.dist-info/METADATA
reserve_name-0.1.2.dist-info/WHEEL
reserve_name-0.1.2.dist-info/entry_points.txt
reserve_name-0.1.2.dist-info/top_level.txt
reserve_name-0.1.2.dist-info/RECORD
