Metadata-Version: 2.4
Name: reserve-name
Version: 0.1.2
Summary: A tool to reserve Python package names on PyPI
Author-email: Your Name <your.email@example.com>
License: MIT
Project-URL: Homepage, https://github.com/yourusername/reserve-name
Project-URL: Repository, https://github.com/yourusername/reserve-name
Project-URL: Issues, https://github.com/yourusername/reserve-name/issues
Keywords: pypi,package,reserve,name
Classifier: Development Status :: 4 - Beta
Classifier: Intended Audience :: Developers
Classifier: License :: OSI Approved :: MIT License
Classifier: Programming Language :: Python :: 3
Classifier: Programming Language :: Python :: 3.8
Classifier: Programming Language :: Python :: 3.9
Classifier: Programming Language :: Python :: 3.10
Classifier: Programming Language :: Python :: 3.11
Classifier: Programming Language :: Python :: 3.12
Requires-Python: >=3.8
Requires-Dist: python-dotenv>=0.19.0
